{"link": "https://www.t66y.com/thread0806.php?fid=16"}
{"link": "https://www.t66y.com/thread0806.php?fid=16"}
{"link": "https://www.t66y.com/notice.php?fid=-1#1"}
{"link": "https://www.t66y.com/read.php?tid=5877"}
{"link": "https://www.t66y.com/htm_data/16/1402/2268779.html"}
{"link": "https://www.t66y.com/htm_data/16/0907/344501.html"}
{"link": "https://www.t66y.com/htm_data/16/0805/136474.html"}
{"link": "https://www.t66y.com/htm_data/16/1106/524942.html"}
{"link": "https://www.t66y.com/htm_data/16/1109/594741.html"}
{"link": "https://www.t66y.com/htm_data/16/1110/622028.html"}
{"link": "https://www.t66y.com/htm_data/16/1706/2424348.html"}
{"link": "https://www.t66y.com/thread0806.php?fid=16"}
{"link": "https://www.t66y.com/htm_data/16/1709/2640916.html"}
{"link": "https://www.t66y.com/htm_data/16/1709/2652681.html"}
{"link": "https://www.t66y.com/htm_data/16/1709/2640882.html"}
{"link": "https://www.t66y.com/htm_data/16/1709/2644411.html"}
{"link": "https://www.t66y.com/htm_data/16/1709/2644128.html"}
{"link": "https://www.t66y.com/htm_data/16/1709/2643964.html"}
{"link": "https://www.t66y.com/htm_data/16/1709/2643315.html"}
{"link": "https://www.t66y.com/htm_data/16/1709/2643768.html"}
{"link": "https://www.t66y.com/htm_data/16/1709/2641273.html"}
{"link": "https://www.t66y.com/htm_data/16/1709/2641242.html"}
{"link": "https://www.t66y.com/htm_data/16/1709/2641194.html"}
{"link": "https://www.t66y.com/htm_data/16/1709/2640873.html"}
{"link": "https://www.t66y.com/htm_data/16/1709/2640885.html"}
{"link": "https://www.t66y.com/htm_data/16/1709/2640314.html"}
{"link": "https://www.t66y.com/htm_data/16/1709/2640291.html"}
{"link": "https://www.t66y.com/htm_data/16/1709/2639825.html"}
{"link": "https://www.t66y.com/htm_data/16/1709/2640099.html"}
{"link": "https://www.t66y.com/htm_data/16/1709/2639522.html"}
{"link": "https://www.t66y.com/htm_data/16/1709/2639536.html"}
{"link": "https://www.t66y.com/htm_data/16/1709/2639147.html"}
{"link": "https://www.t66y.com/htm_data/16/1709/2639022.html"}
{"link": "https://www.t66y.com/htm_data/16/1709/2638633.html"}
{"link": "https://www.t66y.com/htm_data/16/1709/2638790.html"}
{"link": "https://www.t66y.com/htm_data/16/1709/2637866.html"}
{"link": "https://www.t66y.com/htm_data/16/1709/2637408.html"}
{"link": "https://www.t66y.com/htm_data/16/1709/2637262.html"}
{"link": "https://www.t66y.com/htm_data/16/1709/2637034.html"}
{"link": "https://www.t66y.com/htm_data/16/1709/2637032.html"}
{"link": "https://www.t66y.com/htm_data/16/1709/2636886.html"}
{"link": "https://www.t66y.com/htm_data/16/1709/2637003.html"}
{"link": "https://www.t66y.com/htm_data/16/1709/2636766.html"}
{"link": "https://www.t66y.com/htm_data/16/1709/2636446.html"}
{"link": "https://www.t66y.com/htm_data/16/1709/2626400.html"}
{"link": "https://www.t66y.com/htm_data/16/1709/2627014.html"}
{"link": "https://www.t66y.com/htm_data/16/1709/2646970.html"}
{"link": "https://www.t66y.com/htm_data/16/1709/2625629.html"}
{"link": "https://www.t66y.com/htm_data/16/1709/2634123.html"}
{"link": "https://www.t66y.com/htm_data/16/1709/2662304.html"}
{"link": "https://www.t66y.com/htm_data/16/1709/2662089.html"}
{"link": "https://www.t66y.com/htm_data/16/1709/2661828.html"}
{"link": "https://www.t66y.com/htm_data/16/1709/2661815.html"}
{"link": "https://www.t66y.com/htm_data/16/1709/2661746.html"}
{"link": "https://www.t66y.com/htm_data/16/1709/2661730.html"}
{"link": "https://www.t66y.com/htm_data/16/1709/2661672.html"}
{"link": "https://www.t66y.com/htm_data/16/1709/2661631.html"}
{"link": "https://www.t66y.com/htm_data/16/1709/2661624.html"}
{"link": "https://www.t66y.com/htm_data/16/1709/2661633.html"}
{"link": "https://www.t66y.com/htm_data/16/1709/2661603.html"}
{"link": "https://www.t66y.com/htm_data/16/1709/2661350.html"}
{"link": "https://www.t66y.com/htm_data/16/1709/2661481.html"}
{"link": "https://www.t66y.com/htm_data/16/1709/2661334.html"}
{"link": "https://www.t66y.com/htm_data/16/1709/2661333.html"}
{"link": "https://www.t66y.com/htm_data/16/1709/2661021.html"}
{"link": "https://www.t66y.com/htm_data/16/1709/2661046.html"}
{"link": "https://www.t66y.com/htm_data/16/1709/2661615.html"}
{"link": "https://www.t66y.com/htm_data/16/1709/2661574.html"}
{"link": "https://www.t66y.com/htm_data/16/1709/2661569.html"}
{"link": "https://www.t66y.com/htm_data/16/1709/2661555.html"}
{"link": "https://www.t66y.com/htm_data/16/1709/2661531.html"}
{"link": "https://www.t66y.com/htm_data/16/1709/2661527.html"}
{"link": "https://www.t66y.com/htm_data/16/1709/2661523.html"}
{"link": "https://www.t66y.com/htm_data/16/1709/2661522.html"}
{"link": "https://www.t66y.com/htm_data/16/1709/2661508.html"}
{"link": "https://www.t66y.com/htm_data/16/1709/2661490.html"}
{"link": "https://www.t66y.com/htm_data/16/1709/2661331.html"}
{"link": "https://www.t66y.com/htm_data/16/1709/2661241.html"}
{"link": "https://www.t66y.com/htm_data/16/1709/2661182.html"}
{"link": "https://www.t66y.com/htm_data/16/1709/2661179.html"}
{"link": "https://www.t66y.com/htm_data/16/1709/2661175.html"}
{"link": "https://www.t66y.com/htm_data/16/1709/2661173.html"}
{"link": "https://www.t66y.com/htm_data/16/1709/2661171.html"}
{"link": "https://www.t66y.com/htm_data/16/1709/2661169.html"}
{"link": "https://www.t66y.com/htm_data/16/1709/2661157.html"}
{"link": "https://www.t66y.com/htm_data/16/1709/2661156.html"}
{"link": "https://www.t66y.com/htm_data/16/1709/2661149.html"}
{"link": "https://www.t66y.com/htm_data/16/1709/2661148.html"}
{"link": "https://www.t66y.com/htm_data/16/1709/2661137.html"}
{"link": "https://www.t66y.com/htm_data/16/1709/2661136.html"}
{"link": "https://www.t66y.com/htm_data/16/1709/2661120.html"}
{"link": "https://www.t66y.com/htm_data/16/1709/2661117.html"}
{"link": "https://www.t66y.com/htm_data/16/1709/2661095.html"}
{"link": "https://www.t66y.com/htm_data/16/1709/2661079.html"}
{"link": "https://www.t66y.com/htm_data/16/1709/2661072.html"}
{"link": "https://www.t66y.com/htm_data/16/1709/2661071.html"}
{"link": "https://www.t66y.com/htm_data/16/1709/2661029.html"}
{"link": "https://www.t66y.com/htm_data/16/1709/2661019.html"}
{"link": "https://www.t66y.com/htm_data/16/1709/2661012.html"}
{"link": "https://www.t66y.com/htm_data/16/1709/2661009.html"}
{"link": "https://www.t66y.com/htm_data/16/1709/2660984.html"}
{"link": "https://www.t66y.com/htm_data/16/1709/2660969.html"}
{"link": "https://www.t66y.com/htm_data/16/1709/2660862.html"}
{"link": "https://www.t66y.com/htm_data/16/1709/2660831.html"}
{"link": "https://www.t66y.com/thread0806.php?fid=16"}
