{"votes": 836374, "score": "9.4", "movie_name": "这个杀手不太冷", "rank": 1}
{"votes": 764662, "score": "9.2", "movie_name": "盗梦空间", "rank": 2}
{"votes": 489282, "score": "9.2", "movie_name": "大话西游之大圣娶亲", "rank": 3}
{"votes": 74559, "score": "9.2", "movie_name": "七武士", "rank": 4}
{"votes": 284869, "score": "9.1", "movie_name": "指环王3：王者无敌", "rank": 5}
{"votes": 404712, "score": "9.0", "movie_name": "搏击俱乐部", "rank": 6}
{"votes": 319471, "score": "9.0", "movie_name": "蝙蝠侠：黑暗骑士", "rank": 7}
{"votes": 7463, "score": "9.0", "movie_name": "将军号", "rank": 8}
{"votes": 395569, "score": "8.9", "movie_name": "大话西游之月光宝盒", "rank": 9}
{"votes": 300275, "score": "8.9", "movie_name": "指环王1：魔戒再现", "rank": 10}
{"votes": 268826, "score": "8.9", "movie_name": "指环王2：双塔奇兵", "rank": 11}
{"votes": 57754, "score": "8.9", "movie_name": "攻壳机动队", "rank": 12}
{"votes": 413069, "score": "8.8", "movie_name": "V字仇杀队", "rank": 13}
{"votes": 292737, "score": "8.8", "movie_name": "勇敢的心", "rank": 14}
{"votes": 275579, "score": "8.8", "movie_name": "黑客帝国", "rank": 15}
{"votes": 230185, "score": "8.8", "movie_name": "幽灵公主", "rank": 16}
{"votes": 13394, "score": "8.8", "movie_name": "用心棒", "rank": 17}
{"votes": 11500, "score": "8.8", "movie_name": "桥", "rank": 18}
{"votes": 9360, "score": "8.8", "movie_name": "攻壳机动队SSS", "rank": 19}
{"votes": 611057, "score": "8.7", "movie_name": "让子弹飞", "rank": 20}
{"votes": 283908, "score": "8.7", "movie_name": "血战钢锯岭", "rank": 21}
{"votes": 175420, "score": "8.7", "movie_name": "谍影重重3", "rank": 22}
{"votes": 143548, "score": "8.7", "movie_name": "英雄本色", "rank": 23}
{"votes": 137211, "score": "8.7", "movie_name": "纵横四海", "rank": 24}
{"votes": 89364, "score": "8.7", "movie_name": "东邪西毒：终极版", "rank": 25}
{"votes": 70632, "score": "8.7", "movie_name": "小萝莉的猴神大叔", "rank": 26}
{"votes": 44780, "score": "8.7", "movie_name": "精英部队2：大敌当前", "rank": 27}
{"votes": 32191, "score": "8.7", "movie_name": "乱", "rank": 28}
{"votes": 30451, "score": "8.7", "movie_name": "黑客帝国动画版", "rank": 29}
{"votes": 8222, "score": "8.7", "movie_name": "椿三十郎", "rank": 30}
{"votes": 4920, "score": "8.7", "movie_name": "铁达尼号沉没记", "rank": 31}
{"votes": 516546, "score": "8.6", "movie_name": "阿凡达", "rank": 32}
{"votes": 349711, "score": "8.6", "movie_name": "超能陆战队", "rank": 33}
{"votes": 333935, "score": "8.6", "movie_name": "加勒比海盗", "rank": 34}
{"votes": 241607, "score": "8.6", "movie_name": "东邪西毒", "rank": 35}
{"votes": 93599, "score": "8.6", "movie_name": "枪火", "rank": 36}
{"votes": 46997, "score": "8.6", "movie_name": "恶童", "rank": 37}
{"votes": 18680, "score": "8.6", "movie_name": "宾虚", "rank": 38}
{"votes": 15151, "score": "8.6", "movie_name": "蝙蝠侠：黑暗骑士归来(下)", "rank": 39}
{"votes": 8661, "score": "8.6", "movie_name": "敲开天堂的门", "rank": 40}
{"votes": 3805, "score": "8.6", "movie_name": "碧血金沙", "rank": 41}
{"votes": 3714, "score": "8.6", "movie_name": "落叶", "rank": 42}
{"votes": 282119, "score": "8.5", "movie_name": "蝙蝠侠：黑暗骑士崛起", "rank": 43}
{"votes": 248335, "score": "8.5", "movie_name": "被解救的姜戈", "rank": 44}
{"votes": 199626, "score": "8.5", "movie_name": "疯狂的麦克斯4：狂暴之路", "rank": 45}
{"votes": 183798, "score": "8.5", "movie_name": "谍影重重", "rank": 46}
{"votes": 152314, "score": "8.5", "movie_name": "谍影重重2", "rank": 47}
{"votes": 146957, "score": "8.5", "movie_name": "黑客帝国3：矩阵革命", "rank": 48}
{"votes": 136366, "score": "8.5", "movie_name": "勇闯夺命岛", "rank": 49}
{"votes": 134462, "score": "8.5", "movie_name": "终结者2：审判日", "rank": 50}
{"votes": 104441, "score": "8.5", "movie_name": "黑鹰坠落", "rank": 51}
{"votes": 43975, "score": "8.5", "movie_name": "启示", "rank": 52}
{"votes": 7847, "score": "8.5", "movie_name": "午夜狂奔", "rank": 53}
{"votes": 7101, "score": "8.5", "movie_name": "西线无战事", "rank": 54}
{"votes": 5071, "score": "8.5", "movie_name": "大菩萨岭", "rank": 55}
{"votes": 4580, "score": "8.5", "movie_name": "兽兵卫忍风帖", "rank": 56}
{"votes": 3575, "score": "8.5", "movie_name": "盗信情缘", "rank": 57}
{"votes": 1578, "score": "8.5", "movie_name": "通往自由的通道", "rank": 58}
{"votes": 1053, "score": "8.5", "movie_name": "笔中情", "rank": 59}
{"votes": 317802, "score": "8.4", "movie_name": "王牌特工：特工学院", "rank": 60}
{"votes": 207733, "score": "8.4", "movie_name": "速度与激情5", "rank": 61}
{"votes": 205004, "score": "8.4", "movie_name": "变脸", "rank": 62}
{"votes": 173359, "score": "8.4", "movie_name": "新龙门客栈", "rank": 63}
{"votes": 136875, "score": "8.4", "movie_name": "黑客帝国2：重装上阵", "rank": 64}
{"votes": 134356, "score": "8.4", "movie_name": "罪恶之城", "rank": 65}
{"votes": 122393, "score": "8.4", "movie_name": "角斗士", "rank": 66}
{"votes": 111416, "score": "8.4", "movie_name": "暗战", "rank": 67}
{"votes": 102922, "score": "8.4", "movie_name": "神探", "rank": 68}
{"votes": 77607, "score": "8.4", "movie_name": "黄海", "rank": 69}
{"votes": 63707, "score": "8.4", "movie_name": "王牌对王牌", "rank": 70}
{"votes": 63640, "score": "8.4", "movie_name": "盗火线", "rank": 71}
{"votes": 14356, "score": "8.4", "movie_name": "精武门", "rank": 72}
{"votes": 10287, "score": "8.4", "movie_name": "杀死比尔整个血腥事件", "rank": 73}
{"votes": 8589, "score": "8.4", "movie_name": "蜘蛛巢城", "rank": 74}
{"votes": 7410, "score": "8.4", "movie_name": "侠女", "rank": 75}
{"votes": 6926, "score": "8.4", "movie_name": "最长的一天", "rank": 76}
{"votes": 3850, "score": "8.4", "movie_name": "红线", "rank": 77}
{"votes": 3536, "score": "8.4", "movie_name": "飞行器里的好小伙，或我是怎样花25小时11分从伦敦飞到巴黎", "rank": 78}
{"votes": 1985, "score": "8.4", "movie_name": "死亡的游戏", "rank": 79}
{"votes": 1719, "score": "8.4", "movie_name": "福禄双霸天", "rank": 80}
{"votes": 1039, "score": "8.4", "movie_name": "忍者小英雄", "rank": 81}
{"votes": 390916, "score": "8.3", "movie_name": "源代码", "rank": 82}
{"votes": 254117, "score": "8.3", "movie_name": "速度与激情7", "rank": 83}
{"votes": 208090, "score": "8.3", "movie_name": "金刚狼3：殊死一战", "rank": 84}
{"votes": 153088, "score": "8.3", "movie_name": "无间道2", "rank": 85}
{"votes": 91454, "score": "8.3", "movie_name": "买凶拍人", "rank": 86}
{"votes": 84740, "score": "8.3", "movie_name": "热血警探", "rank": 87}
{"votes": 83318, "score": "8.3", "movie_name": "笑傲江湖2：东方不败", "rank": 88}
{"votes": 60007, "score": "8.3", "movie_name": "星球大战", "rank": 89}
{"votes": 51606, "score": "8.3", "movie_name": "太极旗飘扬", "rank": 90}
{"votes": 43709, "score": "8.3", "movie_name": "星球大战3：绝地归来", "rank": 91}
{"votes": 35355, "score": "8.3", "movie_name": "喋血双雄", "rank": 92}
{"votes": 30378, "score": "8.3", "movie_name": "一个字头的诞生", "rank": 93}
{"votes": 19874, "score": "8.3", "movie_name": "荒野大镖客", "rank": 94}
{"votes": 18999, "score": "8.3", "movie_name": "阿基拉", "rank": 95}
{"votes": 4574, "score": "8.3", "movie_name": "日落黄沙", "rank": 96}
{"votes": 4341, "score": "8.3", "movie_name": "胜利之光", "rank": 97}
{"votes": 3869, "score": "8.3", "movie_name": "战国英豪", "rank": 98}
{"votes": 2293, "score": "8.3", "movie_name": "菜鸟总动员：毕业", "rank": 99}
{"votes": 2164, "score": "8.3", "movie_name": "战略大作战", "rank": 100}
{"votes": 2158, "score": "8.3", "movie_name": "飞出个未来大电影2：万背之兽", "rank": 101}
{"votes": 2137, "score": "8.3", "movie_name": "冰海沉船", "rank": 102}
{"votes": 1897, "score": "8.3", "movie_name": "孟菲斯美女号", "rank": 103}
{"votes": 367058, "score": "8.2", "movie_name": "西游记之大圣归来", "rank": 104}
{"votes": 343929, "score": "8.2", "movie_name": "釜山行", "rank": 105}
{"votes": 252663, "score": "8.2", "movie_name": "碟中谍4", "rank": 106}
{"votes": 245279, "score": "8.2", "movie_name": "X战警：逆转未来", "rank": 107}
{"votes": 220001, "score": "8.2", "movie_name": "第九区", "rank": 108}
{"votes": 190005, "score": "8.2", "movie_name": "霍比特人3：五军之战", "rank": 109}
{"votes": 189469, "score": "8.2", "movie_name": "霍比特人2：史矛革之战", "rank": 110}
{"votes": 131751, "score": "8.2", "movie_name": "蝙蝠侠：侠影之谜", "rank": 111}
{"votes": 125545, "score": "8.2", "movie_name": "飓风营救", "rank": 112}
{"votes": 52806, "score": "8.2", "movie_name": "星球大战前传3：西斯的复仇", "rank": 113}
{"votes": 47028, "score": "8.2", "movie_name": "星球大战2：帝国反击战", "rank": 114}
{"votes": 45600, "score": "8.2", "movie_name": "天国王朝", "rank": 115}
{"votes": 39624, "score": "8.2", "movie_name": "最终幻想7：圣子降临", "rank": 116}
{"votes": 32484, "score": "8.2", "movie_name": "处刑人", "rank": 117}
{"votes": 22485, "score": "8.2", "movie_name": "雌雄大盗", "rank": 118}
{"votes": 17373, "score": "8.2", "movie_name": "猛龙过江", "rank": 119}
{"votes": 15445, "score": "8.2", "movie_name": "追捕", "rank": 120}
{"votes": 14565, "score": "8.2", "movie_name": "卡桑德拉大桥", "rank": 121}
{"votes": 13307, "score": "8.2", "movie_name": "大都会", "rank": 122}
{"votes": 10071, "score": "8.2", "movie_name": "正义联盟：闪点悖论", "rank": 123}
{"votes": 6287, "score": "8.2", "movie_name": "蝙蝠侠：红影迷踪", "rank": 124}
{"votes": 6137, "score": "8.2", "movie_name": "白色严冬", "rank": 125}
{"votes": 6087, "score": "8.2", "movie_name": "奏鸣曲", "rank": 126}
{"votes": 5207, "score": "8.2", "movie_name": "老人Z", "rank": 127}
{"votes": 4274, "score": "8.2", "movie_name": "关山飞渡", "rank": 128}
{"votes": 3698, "score": "8.2", "movie_name": "机动警察剧场版1", "rank": 129}
{"votes": 3482, "score": "8.2", "movie_name": "桃色血案", "rank": 130}
{"votes": 2702, "score": "8.2", "movie_name": "天与地", "rank": 131}
{"votes": 2373, "score": "8.2", "movie_name": "迎春阁之风波", "rank": 132}
{"votes": 1425, "score": "8.2", "movie_name": "红河", "rank": 133}
{"votes": 1235, "score": "8.2", "movie_name": "疤面人", "rank": 134}
{"votes": 233879, "score": "8.1", "movie_name": "变形金刚", "rank": 135}
{"votes": 219663, "score": "8.1", "movie_name": "霍比特人1：意外之旅", "rank": 136}
{"votes": 191572, "score": "8.1", "movie_name": "加勒比海盗2：聚魂棺", "rank": 137}
{"votes": 185427, "score": "8.1", "movie_name": "杀死比尔", "rank": 138}
{"votes": 178454, "score": "8.1", "movie_name": "X战警：第一战", "rank": 139}
{"votes": 171079, "score": "8.1", "movie_name": "银河护卫队2", "rank": 140}
{"votes": 157309, "score": "8.1", "movie_name": "铁甲钢拳", "rank": 141}
{"votes": 154851, "score": "8.1", "movie_name": "国产凌凌漆", "rank": 142}
{"votes": 148464, "score": "8.1", "movie_name": "罗拉快跑", "rank": 143}
{"votes": 141980, "score": "8.1", "movie_name": "师父", "rank": 144}
{"votes": 115539, "score": "8.1", "movie_name": "孤胆特工", "rank": 145}
{"votes": 109609, "score": "8.1", "movie_name": "空中监狱", "rank": 146}
{"votes": 96057, "score": "8.1", "movie_name": "真实的谎言", "rank": 147}
{"votes": 70007, "score": "8.1", "movie_name": "国家公敌", "rank": 148}
{"votes": 68358, "score": "8.1", "movie_name": "守望者", "rank": 149}
{"votes": 50809, "score": "8.1", "movie_name": "英雄本色2", "rank": 150}
{"votes": 50709, "score": "8.1", "movie_name": "精武英雄", "rank": 151}
{"votes": 45694, "score": "8.1", "movie_name": "虎胆龙威", "rank": 152}
{"votes": 43271, "score": "8.1", "movie_name": "第一滴血", "rank": 153}
{"votes": 40331, "score": "8.1", "movie_name": "怒火救援", "rank": 154}
{"votes": 38749, "score": "8.1", "movie_name": "监狱风云", "rank": 155}
{"votes": 37592, "score": "8.1", "movie_name": "西北偏北", "rank": 156}
{"votes": 33469, "score": "8.1", "movie_name": "夺宝奇兵3", "rank": 157}
{"votes": 31602, "score": "8.1", "movie_name": "枪王", "rank": 158}
{"votes": 23978, "score": "8.1", "movie_name": "野战排", "rank": 159}
{"votes": 22948, "score": "8.1", "movie_name": "爱国者", "rank": 160}
{"votes": 19388, "score": "8.1", "movie_name": "喋血街头", "rank": 161}
{"votes": 16224, "score": "8.1", "movie_name": "双旗镇刀客", "rank": 162}
{"votes": 15167, "score": "8.1", "movie_name": "爱的曝光", "rank": 163}
{"votes": 13428, "score": "8.1", "movie_name": "小倩", "rank": 164}
{"votes": 10947, "score": "8.1", "movie_name": "龙争虎斗", "rank": 165}
{"votes": 10019, "score": "8.1", "movie_name": "虎！虎！虎！", "rank": 166}
{"votes": 3327, "score": "8.1", "movie_name": "变形金刚大电影", "rank": 167}
{"votes": 3264, "score": "8.1", "movie_name": "痛击", "rank": 168}
{"votes": 3076, "score": "8.1", "movie_name": "山中传奇", "rank": 169}
{"votes": 2658, "score": "8.1", "movie_name": "大饭店", "rank": 170}
{"votes": 2372, "score": "8.1", "movie_name": "跳跃大搜查线：湾岸署史上最恶的3日间", "rank": 171}
{"votes": 1747, "score": "8.1", "movie_name": "血染雪山堡", "rank": 172}
{"votes": 1623, "score": "8.1", "movie_name": "血洗鳄鱼仇", "rank": 173}
{"votes": 1424, "score": "8.1", "movie_name": "忠烈图", "rank": 174}
{"votes": 1152, "score": "8.1", "movie_name": "太秦灯光下", "rank": 175}
{"votes": 1018, "score": "8.1", "movie_name": "摔角狂热 30", "rank": 176}
{"votes": 338797, "score": "8.0", "movie_name": "湄公河行动", "rank": 177}
{"votes": 309591, "score": "8.0", "movie_name": "复仇者联盟", "rank": 178}
{"votes": 260208, "score": "8.0", "movie_name": "功夫熊猫2", "rank": 179}
{"votes": 237506, "score": "8.0", "movie_name": "银河护卫队", "rank": 180}
{"votes": 236332, "score": "8.0", "movie_name": "明日边缘", "rank": 181}
{"votes": 229373, "score": "8.0", "movie_name": "猩球崛起", "rank": 182}
{"votes": 202559, "score": "8.0", "movie_name": "后天", "rank": 183}
{"votes": 179087, "score": "8.0", "movie_name": "加勒比海盗3：世界的尽头", "rank": 184}
{"votes": 127515, "score": "8.0", "movie_name": "大逃杀", "rank": 185}
{"votes": 112910, "score": "8.0", "movie_name": "树大招风", "rank": 186}
{"votes": 106398, "score": "8.0", "movie_name": "暗杀", "rank": 187}
{"votes": 74408, "score": "8.0", "movie_name": "暴力街区", "rank": 188}
{"votes": 74206, "score": "8.0", "movie_name": "天生杀人狂", "rank": 189}
{"votes": 71822, "score": "8.0", "movie_name": "秘密特工", "rank": 190}
{"votes": 70676, "score": "8.0", "movie_name": "生死时速", "rank": 191}
{"votes": 59876, "score": "8.0", "movie_name": "星球大战前传1：幽灵的威胁", "rank": 192}
{"votes": 52919, "score": "8.0", "movie_name": "未知死亡", "rank": 193}
{"votes": 29959, "score": "8.0", "movie_name": "乐高蝙蝠侠大电影", "rank": 194}
{"votes": 27567, "score": "8.0", "movie_name": "天若有情", "rank": 195}
{"votes": 24848, "score": "8.0", "movie_name": "座头市", "rank": 196}
{"votes": 24653, "score": "8.0", "movie_name": "囚室211", "rank": 197}
{"votes": 20896, "score": "8.0", "movie_name": "亡命天涯", "rank": 198}
{"votes": 18836, "score": "8.0", "movie_name": "魁拔Ⅲ战神崛起", "rank": 199}
{"votes": 16829, "score": "8.0", "movie_name": "实尾岛", "rank": 200}
{"votes": 16583, "score": "8.0", "movie_name": "飞天小女警 剧场版", "rank": 201}
{"votes": 13223, "score": "8.0", "movie_name": "蝙蝠侠：黑暗骑士归来(上)", "rank": 202}
{"votes": 10229, "score": "8.0", "movie_name": "佐罗", "rank": 203}
{"votes": 10188, "score": "8.0", "movie_name": "少年菀得", "rank": 204}
{"votes": 5829, "score": "8.0", "movie_name": "龙门客栈", "rank": 205}
{"votes": 4917, "score": "8.0", "movie_name": "野鹅敢死队", "rank": 206}
{"votes": 4751, "score": "8.0", "movie_name": "新独臂刀", "rank": 207}
{"votes": 4232, "score": "8.0", "movie_name": "蝙蝠侠：元年", "rank": 208}
{"votes": 3542, "score": "8.0", "movie_name": "遥远的桥", "rank": 209}
{"votes": 3465, "score": "8.0", "movie_name": "天劫余生", "rank": 210}
{"votes": 2602, "score": "8.0", "movie_name": "侠僧探案传奇之大夜叉", "rank": 211}
{"votes": 2547, "score": "8.0", "movie_name": "笑破铁幕", "rank": 212}
{"votes": 1237, "score": "8.0", "movie_name": "众神与将军", "rank": 213}
{"votes": 287363, "score": "7.9", "movie_name": "功夫熊猫", "rank": 214}
{"votes": 265382, "score": "7.9", "movie_name": "功夫", "rank": 215}
{"votes": 208233, "score": "7.9", "movie_name": "美国队长2", "rank": 216}
{"votes": 168671, "score": "7.9", "movie_name": "疯狂的赛车", "rank": 217}
{"votes": 166144, "score": "7.9", "movie_name": "卧虎藏龙", "rank": 218}
{"votes": 152182, "score": "7.9", "movie_name": "黑衣人", "rank": 219}
{"votes": 147214, "score": "7.9", "movie_name": "星际迷航2：暗黑无界", "rank": 220}
{"votes": 136349, "score": "7.9", "movie_name": "我，机器人", "rank": 221}
{"votes": 134034, "score": "7.9", "movie_name": "独立日", "rank": 222}
{"votes": 125178, "score": "7.9", "movie_name": "超人总动员", "rank": 223}
{"votes": 124345, "score": "7.9", "movie_name": "碟中谍", "rank": 224}
{"votes": 123213, "score": "7.9", "movie_name": "第五元素", "rank": 225}
{"votes": 101786, "score": "7.9", "movie_name": "十一罗汉", "rank": 226}
{"votes": 96503, "score": "7.9", "movie_name": "星际迷航", "rank": 227}
{"votes": 93601, "score": "7.9", "movie_name": "终结者", "rank": 228}
{"votes": 59320, "score": "7.9", "movie_name": "危情三日", "rank": 229}
{"votes": 59043, "score": "7.9", "movie_name": "黄飞鸿", "rank": 230}
{"votes": 58868, "score": "7.9", "movie_name": "异形2", "rank": 231}
{"votes": 39939, "score": "7.9", "movie_name": "狗咬狗", "rank": 232}
{"votes": 34619, "score": "7.9", "movie_name": "少林寺", "rank": 233}
{"votes": 29476, "score": "7.9", "movie_name": "孤独的幸存者", "rank": 234}
{"votes": 26910, "score": "7.9", "movie_name": "精英部队", "rank": 235}
{"votes": 23573, "score": "7.9", "movie_name": "决战犹马镇", "rank": 236}
{"votes": 22467, "score": "7.9", "movie_name": "猎杀U-571", "rank": 237}
{"votes": 19479, "score": "7.9", "movie_name": "辣手神探", "rank": 238}
{"votes": 18238, "score": "7.9", "movie_name": "僵尸先生", "rank": 239}
{"votes": 18179, "score": "7.9", "movie_name": "警戒结束", "rank": 240}
{"votes": 17805, "score": "7.9", "movie_name": "刀", "rank": 241}
{"votes": 13450, "score": "7.9", "movie_name": "太阳帝国", "rank": 242}
{"votes": 6067, "score": "7.9", "movie_name": "斯巴达克斯", "rank": 243}
{"votes": 5524, "score": "7.9", "movie_name": "红潮风暴", "rank": 244}
{"votes": 4998, "score": "7.9", "movie_name": "洛奇3", "rank": 245}
{"votes": 4015, "score": "7.9", "movie_name": "势不两立", "rank": 246}
{"votes": 2720, "score": "7.9", "movie_name": "省港旗兵4：地下通道", "rank": 247}
{"votes": 2486, "score": "7.9", "movie_name": "飞出个未来大电影3：班德的游戏", "rank": 248}
{"votes": 2130, "score": "7.9", "movie_name": "跳跃大搜查线最终篇：新的希望", "rank": 249}
{"votes": 1734, "score": "7.9", "movie_name": "报仇", "rank": 250}
{"votes": 1586, "score": "7.9", "movie_name": "达摩祖师", "rank": 251}
{"votes": 1564, "score": "7.9", "movie_name": "第一类型危险", "rank": 252}
{"votes": 1531, "score": "7.9", "movie_name": "猫头鹰", "rank": 253}
